API/__init__.py
API/api.py
API/Converters/__init__.py
API/Converters/ignoretext.py
valorant_killsound-0.0.3.dist-info/LICENSE
valorant_killsound-0.0.3.dist-info/METADATA
valorant_killsound-0.0.3.dist-info/WHEEL
valorant_killsound-0.0.3.dist-info/top_level.txt
valorant_killsound-0.0.3.dist-info/RECORD
