Metadata-Version: 2.1
Name: valorant-killsound
Version: 0.0.3
Summary: An API for piu piu game.
Home-page: https://github.com/qing762/valorant_killsound
Author: qing762
Author-email: threatedblade@outlook.com
Keywords: python,api,python wrapper,valorant,valorant-api,valorant api,piu piu game,sound effects,reaver,sovereign,ion,prime,kill sound,valorant gun skins
Classifier: Development Status :: 2 - Pre-Alpha
Classifier: Intended Audience :: Developers
Classifier: Intended Audience :: Education
Classifier: Programming Language :: Python :: 3
Classifier: Operating System :: Unix
Classifier: Operating System :: MacOS :: MacOS X
Classifier: Operating System :: Microsoft :: Windows
License-File: LICENSE
Requires-Dist: beautifulsoup4
Requires-Dist: requests
Requires-Dist: setuptools
